odoo/addons/sale_product_pack/README.rst
odoo/addons/sale_product_pack/__init__.py
odoo/addons/sale_product_pack/__manifest__.py
odoo/addons/sale_product_pack/demo/product_pack_line_demo.xml
odoo/addons/sale_product_pack/demo/sale_pack_demo.xml
odoo/addons/sale_product_pack/i18n/ca.po
odoo/addons/sale_product_pack/i18n/ca_ES.po
odoo/addons/sale_product_pack/i18n/es.po
odoo/addons/sale_product_pack/i18n/fr.po
odoo/addons/sale_product_pack/i18n/it.po
odoo/addons/sale_product_pack/i18n/nl.po
odoo/addons/sale_product_pack/i18n/pt.po
odoo/addons/sale_product_pack/i18n/sale_product_pack.pot
odoo/addons/sale_product_pack/models/__init__.py
odoo/addons/sale_product_pack/models/product_pack_line.py
odoo/addons/sale_product_pack/models/sale_order.py
odoo/addons/sale_product_pack/models/sale_order_line.py
odoo/addons/sale_product_pack/readme/CONTRIBUTORS.md
odoo/addons/sale_product_pack/readme/DESCRIPTION.md
odoo/addons/sale_product_pack/readme/ROADMAP.md
odoo/addons/sale_product_pack/readme/USAGE.md
odoo/addons/sale_product_pack/security/ir.model.access.csv
odoo/addons/sale_product_pack/static/description/icon.png
odoo/addons/sale_product_pack/static/description/index.html
odoo/addons/sale_product_pack/tests/__init__.py
odoo/addons/sale_product_pack/tests/common.py
odoo/addons/sale_product_pack/tests/test_sale_product_pack.py
odoo/addons/sale_product_pack/views/product_pack_line_views.xml
odoo_addon_sale_product_pack-18.0.1.0.2.dist-info/METADATA
odoo_addon_sale_product_pack-18.0.1.0.2.dist-info/WHEEL
odoo_addon_sale_product_pack-18.0.1.0.2.dist-info/top_level.txt
odoo_addon_sale_product_pack-18.0.1.0.2.dist-info/RECORD
